flask_gzip.py
Flask_gzip-0.2.dist-info/METADATA
Flask_gzip-0.2.dist-info/WHEEL
Flask_gzip-0.2.dist-info/top_level.txt
Flask_gzip-0.2.dist-info/RECORD
