Metadata-Version: 2.1
Name: Flask-gzip
Version: 0.2
Summary: Compress responses in your Flask app with gzip.
Home-page: https://github.com/closeio/flask-gzip
Author: Close Engineering
Author-email: engineering@close.com
License: BSD
Platform: any
Classifier: Environment :: Web Environment
Classifier: Intended Audience :: Developers
Classifier: License :: OSI Approved :: BSD License
Classifier: Operating System :: OS Independent
Classifier: Programming Language :: Python
Classifier: Programming Language :: Python :: 3
Classifier: Topic :: Internet :: WWW/HTTP :: Dynamic Content
Classifier: Topic :: Software Development :: Libraries :: Python Modules
Requires-Dist: Flask
